setup.py
fibonacci/__init__.py
fibonacci/finonacci.py
fibonacci_library.egg-info/PKG-INFO
fibonacci_library.egg-info/SOURCES.txt
fibonacci_library.egg-info/dependency_links.txt
fibonacci_library.egg-info/top_level.txt