Metadata-Version: 2.1
Name: fibonacci-library
Version: 0.1
Summary: A Simple Python library for generate fibonacci series
Author: Rakesh Kumar
